Metadata-Version: 2.1
Name: logdebug
Version: 0.0.1
Summary: Logging And Exception
Author-email: ranjitmaity95@gmail.com
